mxcpctl/__init__.py
mxcpctl/cli.py
mxcpctl-0.0.7.dist-info/METADATA
mxcpctl-0.0.7.dist-info/WHEEL
mxcpctl-0.0.7.dist-info/entry_points.txt
mxcpctl-0.0.7.dist-info/top_level.txt
mxcpctl-0.0.7.dist-info/RECORD
