Metadata-Version: 2.4
Name: mxcpctl
Version: 0.0.7
Summary: CLI tool for managing MXCP instances via mxcpd
Requires-Python: >=3.11
Requires-Dist: click>=8.1.0
Requires-Dist: httpx>=0.25.0
Requires-Dist: rich>=13.0.0
Requires-Dist: pyyaml>=6.0
Provides-Extra: dev
Requires-Dist: pytest>=7.4.0; extra == "dev"
Requires-Dist: black>=23.0.0; extra == "dev"
Requires-Dist: ruff>=0.1.0; extra == "dev"
Requires-Dist: mypy>=1.6.0; extra == "dev"
Requires-Dist: build>=1.0.0; extra == "dev"
Requires-Dist: twine>=4.0.0; extra == "dev"
